orionframework/__init__.py
orionframework/email.py
orionframework/middleware.py
orionframework/mixins.py
orionframework/models.py
orionframework/serializers.py
orionframework/vos.py
orionframework/activator/__init__.py
orionframework/activator/mixins.py
orionframework/authentication/__init__.py
orionframework/authentication/backend.py
orionframework/authentication/mixins.py
orionframework/authentication/serializers.py
orionframework/authored/__init__.py
orionframework/authored/models.py
orionframework/authored/serializers.py
orionframework/authored/settings.py
orionframework/aws/__init__.py
orionframework/aws/s3.py
orionframework/batch/__init__.py
orionframework/brazil/__init__.py
orionframework/brazil/cnpj.py
orionframework/copyable/__init__.py
orionframework/copyable/models.py
orionframework/db/__init__.py
orionframework/db/routers.py
orionframework/drf/__init__.py
orionframework/drf/utils.py
orionframework/geo/__init__.py
orionframework/geo/serializers.py
orionframework/google/__init__.py
orionframework/google/firebase/__init__.py
orionframework/google/firestore/__init__.py
orionframework/google/firestore/services.py
orionframework/google/maps/__init__.py
orionframework/google/maps/models.py
orionframework/google/maps/services.py
orionframework/indexable/__init__.py
orionframework/indexable/mixins.py
orionframework/indexable/models.py
orionframework/media/__init__.py
orionframework/media/checksum.py
orionframework/media/content_type.py
orionframework/media/filterset.py
orionframework/media/mixins.py
orionframework/media/models.py
orionframework/media/path_resolvers.py
orionframework/media/registry.py
orionframework/media/serializers.py
orionframework/media/services.py
orionframework/media/settings.py
orionframework/media/utils.py
orionframework/media/vos.py
orionframework/media/cloud_document/__init__.py
orionframework/media/cloud_document/admin.py
orionframework/media/cloud_document/models.py
orionframework/media/cloud_document/serializers.py
orionframework-1.0.67.dist-info/METADATA
orionframework-1.0.67.dist-info/WHEEL
orionframework-1.0.67.dist-info/top_level.txt
orionframework-1.0.67.dist-info/RECORD
