Metadata-Version: 2.1
Name: orionframework
Version: 1.0.67
Summary: A python companion library for the Orion Framework
Home-page: UNKNOWN
Author: Orion Framework
Author-email: orionframework@gmail.com
License: UNKNOWN
Platform: UNKNOWN
Classifier: Programming Language :: Python :: 3
Classifier: License :: OSI Approved :: MIT License
Classifier: Operating System :: OS Independent
